{
  "generated_at": "2026-04-19T16:21:30.918968Z",
  "tracks": {
    "trump_approval": {
      "label": "Trump Job Approval",
      "subtitle": "Weighted average of recent national polls",
      "last_updated": "2026-04-15",
      "polls_in_average": 67,
      "current": {
        "approve": 38.1,
        "disapprove": 57.2,
        "net": -19.1
      },
      "history": [
        {
          "date": "2026-03-05",
          "approve": 40.0,
          "disapprove": 58.0
        },
        {
          "date": "2026-03-20",
          "approve": 43.0,
          "disapprove": 56.0
        },
        {
          "date": "2026-03-23",
          "approve": 34.8,
          "disapprove": 59.7
        },
        {
          "date": "2026-03-26",
          "approve": 38.6,
          "disapprove": 57.7
        },
        {
          "date": "2026-03-29",
          "approve": 43.2,
          "disapprove": 54.0
        },
        {
          "date": "2026-04-01",
          "approve": 33.9,
          "disapprove": 61.1
        },
        {
          "date": "2026-04-04",
          "approve": 39.6,
          "disapprove": 55.9
        },
        {
          "date": "2026-04-07",
          "approve": 39.1,
          "disapprove": 55.3
        },
        {
          "date": "2026-04-10",
          "approve": 41.6,
          "disapprove": 56.6
        },
        {
          "date": "2026-04-13",
          "approve": 39.0,
          "disapprove": 56.4
        },
        {
          "date": "2026-04-16",
          "approve": 45.0,
          "disapprove": 53.0
        }
      ],
      "polls_used": [
        {
          "pollster": "Big Data Poll",
          "end_date": "2026-03-24",
          "sample_size": "3003",
          "approve": 42.0,
          "disapprove": 56.0,
          "weight": 0.104
        },
        {
          "pollster": "AP-NORC",
          "end_date": "2026-03-23",
          "sample_size": "1150",
          "approve": 38.0,
          "disapprove": 60.0,
          "weight": 0.2145
        },
        {
          "pollster": "Quinnipiac University",
          "end_date": "2026-03-23",
          "sample_size": "1191",
          "approve": 38.0,
          "disapprove": 56.0,
          "weight": 0.2183
        },
        {
          "pollster": "Beach Research/Shaw & Co. Research",
          "end_date": "2026-03-23",
          "sample_size": "1001",
          "approve": 41.0,
          "disapprove": 59.0,
          "weight": 0.06
        },
        {
          "pollster": "Quantus Insights",
          "end_date": "2026-03-26",
          "sample_size": 1472,
          "approve": 42.2,
          "disapprove": 56.6,
          "weight": 0.1213
        },
        {
          "pollster": "RMG Research",
          "end_date": "2026-03-26",
          "sample_size": 3000,
          "approve": 45.0,
          "disapprove": 54.0,
          "weight": 0.1039
        },
        {
          "pollster": "UMass/Amherst",
          "end_date": "2026-03-25",
          "sample_size": "000",
          "approve": 33.0,
          "disapprove": 62.0,
          "weight": 0.018
        },
        {
          "pollster": "YouGov",
          "end_date": "2026-03-25",
          "sample_size": null,
          "approve": 32.0,
          "disapprove": 62.0,
          "weight": 0.06
        },
        {
          "pollster": "University of Massachusetts Department of Political Science/YouGov",
          "end_date": "2026-03-25",
          "sample_size": 1000,
          "approve": 33.0,
          "disapprove": 62.0,
          "weight": 0.2
        },
        {
          "pollster": "",
          "end_date": "2026-03-31",
          "sample_size": "2025",
          "approve": 22.0,
          "disapprove": 65.0,
          "weight": 0.0854
        },
        {
          "pollster": "",
          "end_date": "2026-03-30",
          "sample_size": "679",
          "approve": 35.0,
          "disapprove": 58.0,
          "weight": 0.0494
        },
        {
          "pollster": "",
          "end_date": "2026-03-20",
          "sample_size": null,
          "approve": 46.0,
          "disapprove": 54.0,
          "weight": 0.018
        },
        {
          "pollster": "YouGov",
          "end_date": "2026-03-30",
          "sample_size": null,
          "approve": 35.0,
          "disapprove": 58.0,
          "weight": 0.06
        },
        {
          "pollster": "JL Partners",
          "end_date": "2026-03-27",
          "sample_size": null,
          "approve": 46.0,
          "disapprove": 54.0,
          "weight": 0.018
        },
        {
          "pollster": "",
          "end_date": "2026-03-30",
          "sample_size": "201",
          "approve": 35.0,
          "disapprove": 64.0,
          "weight": 0.0269
        },
        {
          "pollster": "SSRS",
          "end_date": "2026-03-30",
          "sample_size": "2025",
          "approve": 20.0,
          "disapprove": 80.0,
          "weight": 0.0854
        },
        {
          "pollster": "CNN/SSRS",
          "end_date": "2026-03-30",
          "sample_size": "201",
          "approve": 35.0,
          "disapprove": 64.0,
          "weight": 0.0269
        },
        {
          "pollster": "SSRS",
          "end_date": "2026-03-30",
          "sample_size": null,
          "approve": 35.0,
          "disapprove": 64.0,
          "weight": 0.018
        },
        {
          "pollster": "J.L. Partners",
          "end_date": "2026-03-24",
          "sample_size": 1019,
          "approve": 41.0,
          "disapprove": 49.0,
          "weight": 0.0606
        },
        {
          "pollster": "YouGov",
          "end_date": "2026-03-30",
          "sample_size": 1505,
          "approve": 39.0,
          "disapprove": 58.0,
          "weight": 0.2454
        },
        {
          "pollster": "YouGov",
          "end_date": "2026-03-30",
          "sample_size": 1679,
          "approve": 35.0,
          "disapprove": 58.0,
          "weight": 0.2592
        },
        {
          "pollster": "CNN/SSRS",
          "end_date": "2026-03-30",
          "sample_size": 1201,
          "approve": 35.0,
          "disapprove": 64.0,
          "weight": 0.0658
        },
        {
          "pollster": "Morning Consult",
          "end_date": "2026-03-29",
          "sample_size": 2203,
          "approve": 43.0,
          "disapprove": 54.0,
          "weight": 0.2226
        },
        {
          "pollster": "ActiVote",
          "end_date": "2026-03-31",
          "sample_size": 598,
          "approve": 42.0,
          "disapprove": 55.0,
          "weight": 0.0464
        },
        {
          "pollster": "RMG Research",
          "end_date": "2026-04-02",
          "sample_size": 3000,
          "approve": 40.0,
          "disapprove": 58.0,
          "weight": 0.1039
        },
        {
          "pollster": "Morning Consult",
          "end_date": "2026-04-07",
          "sample_size": 45000,
          "approve": 39.0,
          "disapprove": 55.0,
          "weight": 2.0125
        },
        {
          "pollster": "Global Strategy Group",
          "end_date": "2026-04-06",
          "sample_size": 1000,
          "approve": 40.0,
          "disapprove": 58.0,
          "weight": 0.12
        },
        {
          "pollster": "TIPP Insights",
          "end_date": "2026-04-02",
          "sample_size": 1464,
          "approve": 39.0,
          "disapprove": 53.0,
          "weight": 0.0726
        },
        {
          "pollster": "YouGov",
          "end_date": "2026-04-06",
          "sample_size": 1560,
          "approve": 41.0,
          "disapprove": 56.0,
          "weight": 0.4996
        },
        {
          "pollster": "YouGov",
          "end_date": "2026-04-06",
          "sample_size": 1750,
          "approve": 38.0,
          "disapprove": 55.0,
          "weight": 0.5292
        },
        {
          "pollster": "RMG Research",
          "end_date": "2026-04-09",
          "sample_size": 4000,
          "approve": 45.0,
          "disapprove": 54.0,
          "weight": 0.24
        },
        {
          "pollster": "J.L. Partners",
          "end_date": "2026-04-08",
          "sample_size": 1013,
          "approve": 39.0,
          "disapprove": 52.0,
          "weight": 0.1208
        },
        {
          "pollster": "YouGov",
          "end_date": "2026-04-10",
          "sample_size": 2387,
          "approve": 39.0,
          "disapprove": 61.0,
          "weight": 0.618
        },
        {
          "pollster": "Quinnipiac University",
          "end_date": "2026-04-13",
          "sample_size": 1028,
          "approve": 38.0,
          "disapprove": 55.0,
          "weight": 0.659
        },
        {
          "pollster": "YouGov",
          "end_date": "2026-04-13",
          "sample_size": 1573,
          "approve": 41.0,
          "disapprove": 58.0,
          "weight": 0.8152
        },
        {
          "pollster": "YouGov",
          "end_date": "2026-04-13",
          "sample_size": 1748,
          "approve": 38.0,
          "disapprove": 56.0,
          "weight": 0.8594
        },
        {
          "pollster": "Morning Consult",
          "end_date": "2026-04-09",
          "sample_size": 2200,
          "approve": 44.0,
          "disapprove": 53.0,
          "weight": 0.445
        },
        {
          "pollster": "RMG Research",
          "end_date": "2026-04-15",
          "sample_size": 3000,
          "approve": 45.0,
          "disapprove": 53.0,
          "weight": 0.3377
        },
        {
          "pollster": "Economist / YouGov",
          "end_date": "2026-03-23",
          "sample_size": "N/A",
          "approve": 36.0,
          "disapprove": 55.0,
          "weight": 0.06
        },
        {
          "pollster": "The Economist / YouGov",
          "end_date": "2026-03-30",
          "sample_size": "unknown",
          "approve": 35.0,
          "disapprove": 58.0,
          "weight": 0.06
        },
        {
          "pollster": "The Economist / YouGov",
          "end_date": "2026-04-06",
          "sample_size": "Not specified",
          "approve": 38.0,
          "disapprove": 55.0,
          "weight": 0.12
        },
        {
          "pollster": "The Associated Press-NORC Center for Public Affairs Research",
          "end_date": "2026-03-23",
          "sample_size": "1150",
          "approve": 38.0,
          "disapprove": 60.0,
          "weight": 0.0643
        },
        {
          "pollster": "The Associated Press-NORC Center for Public Affairs Research",
          "end_date": "2026-03-23",
          "sample_size": "1150",
          "approve": 38.0,
          "disapprove": 60.0,
          "weight": 0.0643
        },
        {
          "pollster": "The Associated Press-NORC Center for Public Affairs Research",
          "end_date": "2026-03-23",
          "sample_size": "1150",
          "approve": 38.0,
          "disapprove": 61.0,
          "weight": 0.0643
        },
        {
          "pollster": "The Associated Press-NORC Center for Public Affairs Research",
          "end_date": "2026-03-23",
          "sample_size": "1150",
          "approve": 38.0,
          "disapprove": 61.0,
          "weight": 0.0643
        },
        {
          "pollster": "The Associated Press-NORC Center for Public Affairs Research",
          "end_date": "2026-03-23",
          "sample_size": "1150",
          "approve": 34.0,
          "disapprove": 64.0,
          "weight": 0.0643
        },
        {
          "pollster": "The Associated Press-NORC Center for Public Affairs Research",
          "end_date": "2026-03-23",
          "sample_size": "1150",
          "approve": 35.0,
          "disapprove": 63.0,
          "weight": 0.0643
        },
        {
          "pollster": "The Associated Press-NORC Center for Public Affairs Research",
          "end_date": "2026-03-23",
          "sample_size": "1150",
          "approve": 36.0,
          "disapprove": 62.0,
          "weight": 0.0643
        },
        {
          "pollster": "The Associated Press-NORC Center for Public Affairs Research",
          "end_date": "2026-03-23",
          "sample_size": "1150",
          "approve": 20.0,
          "disapprove": 48.0,
          "weight": 0.0643
        },
        {
          "pollster": "The Associated Press-NORC Center for Public Affairs Research",
          "end_date": "2026-03-23",
          "sample_size": "1150",
          "approve": 38.0,
          "disapprove": 61.0,
          "weight": 0.0643
        },
        {
          "pollster": "The Associated Press-NORC Center for Public Affairs Research",
          "end_date": "2026-03-23",
          "sample_size": "1150",
          "approve": 38.0,
          "disapprove": 61.0,
          "weight": 0.0643
        },
        {
          "pollster": "The Associated Press-NORC Center for Public Affairs Research",
          "end_date": "2026-03-23",
          "sample_size": "1150",
          "approve": 34.0,
          "disapprove": 64.0,
          "weight": 0.0643
        },
        {
          "pollster": "The Associated Press-NORC Center for Public Affairs Research",
          "end_date": "2026-03-23",
          "sample_size": "1150",
          "approve": 35.0,
          "disapprove": 63.0,
          "weight": 0.0643
        },
        {
          "pollster": "The Associated Press-NORC Center for Public Affairs Research",
          "end_date": "2026-03-23",
          "sample_size": "1150",
          "approve": 36.0,
          "disapprove": 62.0,
          "weight": 0.0643
        },
        {
          "pollster": "AP-NORC Center for Public Affairs Research",
          "end_date": "2026-03-23",
          "sample_size": "1150",
          "approve": 20.0,
          "disapprove": 48.0,
          "weight": 0.2145
        },
        {
          "pollster": "AP-NORC Center for Public Affairs Research",
          "end_date": "2026-03-23",
          "sample_size": "1150",
          "approve": 38.0,
          "disapprove": 61.0,
          "weight": 0.2145
        },
        {
          "pollster": "AP-NORC Center for Public Affairs Research",
          "end_date": "2026-03-23",
          "sample_size": "1150",
          "approve": 38.0,
          "disapprove": 61.0,
          "weight": 0.2145
        },
        {
          "pollster": "AP-NORC Center for Public Affairs Research",
          "end_date": "2026-03-23",
          "sample_size": "1150",
          "approve": 34.0,
          "disapprove": 64.0,
          "weight": 0.2145
        },
        {
          "pollster": "AP-NORC Center for Public Affairs Research",
          "end_date": "2026-03-23",
          "sample_size": "1150",
          "approve": 35.0,
          "disapprove": 63.0,
          "weight": 0.2145
        },
        {
          "pollster": "AP-NORC Center for Public Affairs Research",
          "end_date": "2026-03-23",
          "sample_size": "1150",
          "approve": 36.0,
          "disapprove": 62.0,
          "weight": 0.2145
        },
        {
          "pollster": "Associated Press-NORC Center for Public Affairs Research",
          "end_date": "2026-03-23",
          "sample_size": "1150",
          "approve": 20.0,
          "disapprove": 48.0,
          "weight": 0.0643
        },
        {
          "pollster": "Associated Press-NORC Center for Public Affairs Research",
          "end_date": "2026-03-23",
          "sample_size": "1150",
          "approve": 38.0,
          "disapprove": 61.0,
          "weight": 0.0643
        },
        {
          "pollster": "Associated Press-NORC Center for Public Affairs Research",
          "end_date": "2026-03-23",
          "sample_size": "1150",
          "approve": 38.0,
          "disapprove": 61.0,
          "weight": 0.0643
        },
        {
          "pollster": "Associated Press-NORC Center for Public Affairs Research",
          "end_date": "2026-03-23",
          "sample_size": "1150",
          "approve": 34.0,
          "disapprove": 64.0,
          "weight": 0.0643
        },
        {
          "pollster": "Associated Press-NORC Center for Public Affairs Research",
          "end_date": "2026-03-23",
          "sample_size": "1150",
          "approve": 35.0,
          "disapprove": 63.0,
          "weight": 0.0643
        },
        {
          "pollster": "Associated Press-NORC Center for Public Affairs Research",
          "end_date": "2026-03-23",
          "sample_size": "1150",
          "approve": 36.0,
          "disapprove": 62.0,
          "weight": 0.0643
        },
        {
          "pollster": "Economist / YouGov",
          "end_date": "2026-04-13",
          "sample_size": "N/A",
          "approve": 38.0,
          "disapprove": 56.0,
          "weight": 0.195
        }
      ]
    },
    "generic_ballot": {
      "label": "2026 Generic Congressional Ballot",
      "subtitle": "Which party's candidate would you vote for in your congressional district?",
      "last_updated": "2026-04-15",
      "polls_in_average": 24,
      "current": {
        "dem": 43.9,
        "rep": 39.9,
        "dem_lead": 4.0
      },
      "history": [
        {
          "date": "2026-03-17",
          "dem": 45.0,
          "rep": 39.0
        },
        {
          "date": "2026-03-23",
          "dem": 47.9,
          "rep": 41.1
        },
        {
          "date": "2026-03-26",
          "dem": 48.7,
          "rep": 42.7
        },
        {
          "date": "2026-03-29",
          "dem": 45.0,
          "rep": 42.0
        },
        {
          "date": "2026-04-01",
          "dem": 42.8,
          "rep": 36.8
        },
        {
          "date": "2026-04-04",
          "dem": 49.0,
          "rep": 43.0
        },
        {
          "date": "2026-04-07",
          "dem": 42.1,
          "rep": 39.8
        },
        {
          "date": "2026-04-10",
          "dem": 46.8,
          "rep": 42.6
        },
        {
          "date": "2026-04-13",
          "dem": 41.4,
          "rep": 37.4
        },
        {
          "date": "2026-04-16",
          "dem": 47.0,
          "rep": 43.0
        }
      ],
      "polls_used": [
        {
          "pollster": "Big Data Poll",
          "end_date": "2026-03-24",
          "sample_size": "3003",
          "dem": 48.0,
          "rep": 40.0,
          "weight": 0.104
        },
        {
          "pollster": "Quinnipiac University",
          "end_date": "2026-03-23",
          "sample_size": "1191",
          "dem": 51.0,
          "rep": 40.0,
          "weight": 0.2183
        },
        {
          "pollster": "Quantus Insights",
          "end_date": "2026-03-26",
          "sample_size": 1470,
          "dem": 47.0,
          "rep": 41.3,
          "weight": 0.1212
        },
        {
          "pollster": "Quantus",
          "end_date": "2026-03-26",
          "sample_size": null,
          "dem": 47.0,
          "rep": 41.0,
          "weight": 0.03
        },
        {
          "pollster": "HarrisX/Harris",
          "end_date": "2026-03-26",
          "sample_size": 2009,
          "dem": 51.0,
          "rep": 49.0,
          "weight": 0.085
        },
        {
          "pollster": "Harvard Harris",
          "end_date": "2026-03-26",
          "sample_size": null,
          "dem": 52.0,
          "rep": 48.0,
          "weight": 0.018
        },
        {
          "pollster": "YouGov",
          "end_date": "2026-03-30",
          "sample_size": null,
          "dem": 45.0,
          "rep": 39.0,
          "weight": 0.06
        },
        {
          "pollster": "Sienna",
          "end_date": "2026-03-26",
          "sample_size": null,
          "dem": 52.0,
          "rep": 35.0,
          "weight": 0.018
        },
        {
          "pollster": "Morning Consult",
          "end_date": "2026-03-22",
          "sample_size": null,
          "dem": 47.0,
          "rep": 42.0,
          "weight": 0.045
        },
        {
          "pollster": "YouGov",
          "end_date": "2026-03-30",
          "sample_size": 1502,
          "dem": 45.0,
          "rep": 39.0,
          "weight": 0.2451
        },
        {
          "pollster": "YouGov",
          "end_date": "2026-03-30",
          "sample_size": 1674,
          "dem": 39.0,
          "rep": 33.0,
          "weight": 0.2588
        },
        {
          "pollster": "CNN/SSRS",
          "end_date": "2026-03-30",
          "sample_size": 951,
          "dem": 48.0,
          "rep": 42.0,
          "weight": 0.0585
        },
        {
          "pollster": "Morning Consult",
          "end_date": "2026-03-29",
          "sample_size": 26725,
          "dem": 45.0,
          "rep": 42.0,
          "weight": 0.7754
        },
        {
          "pollster": "Morning Consult",
          "end_date": "2026-03-29",
          "sample_size": "2026",
          "dem": 45.0,
          "rep": 42.0,
          "weight": 0.2135
        },
        {
          "pollster": "Cygnal",
          "end_date": "2026-04-03",
          "sample_size": 1500,
          "dem": 49.0,
          "rep": 43.0,
          "weight": 0.0735
        },
        {
          "pollster": "Morning Consult",
          "end_date": "2026-04-06",
          "sample_size": 2200,
          "dem": 45.0,
          "rep": 42.0,
          "weight": 0.445
        },
        {
          "pollster": "YouGov",
          "end_date": "2026-04-06",
          "sample_size": 1558,
          "dem": 44.0,
          "rep": 42.0,
          "weight": 0.4993
        },
        {
          "pollster": "YouGov",
          "end_date": "2026-04-06",
          "sample_size": 1745,
          "dem": 38.0,
          "rep": 36.0,
          "weight": 0.5284
        },
        {
          "pollster": "RMG Research",
          "end_date": "2026-04-09",
          "sample_size": 2000,
          "dem": 49.0,
          "rep": 44.0,
          "weight": 0.1697
        },
        {
          "pollster": "YouGov",
          "end_date": "2026-04-13",
          "sample_size": 1571,
          "dem": 45.0,
          "rep": 40.0,
          "weight": 0.8147
        },
        {
          "pollster": "YouGov",
          "end_date": "2026-04-13",
          "sample_size": 1745,
          "dem": 38.0,
          "rep": 35.0,
          "weight": 0.8586
        },
        {
          "pollster": "Morning Consult",
          "end_date": "2026-04-09",
          "sample_size": 2200,
          "dem": 46.0,
          "rep": 42.0,
          "weight": 0.445
        },
        {
          "pollster": "McLaughlin & Associates",
          "end_date": "2026-04-15",
          "sample_size": 1000,
          "dem": 47.0,
          "rep": 43.0,
          "weight": 0.195
        },
        {
          "pollster": "YouGov",
          "end_date": "2026-03-23",
          "sample_size": "1150",
          "dem": 45.0,
          "rep": 42.0,
          "weight": 0.2145
        }
      ]
    },
    "lp_inclusion": {
      "label": "Third-Party Inclusion Rate",
      "subtitle": "How often do pollsters include Libertarian candidates?",
      "last_updated": "2026-04-19",
      "total_polls": 23,
      "lp_included": 0,
      "lp_pct": 0.0,
      "example_races": []
    },
    "iran_military": {
      "label": "U.S. Military Action in Iran",
      "subtitle": "Has U.S. military action against Iran gone too far?",
      "last_updated": "2026-03-23",
      "polls_in_average": 19,
      "current": {
        "pos": 49.0,
        "neg": 24.2,
        "net": 24.8,
        "pos_label": "Gone Too Far",
        "neg_label": "About Right"
      },
      "polls_used": [
        {
          "pollster": "The Associated Press-NORC Center for Public Affairs Research",
          "subject": "U.S. Military Action Against Iran \u2014 Gone Too Far?",
          "end_date": "2026-03-23",
          "sample_size": "1150",
          "pos": 59.0,
          "neg": 13.0,
          "weight": 0.0643
        },
        {
          "pollster": "The Associated Press-NORC Center for Public Affairs Research",
          "subject": "Favor Conducting Airstrikes Against Military Targets Inside Iran",
          "end_date": "2026-03-23",
          "sample_size": "1150",
          "pos": 39.0,
          "neg": 26.0,
          "weight": 0.0643
        },
        {
          "pollster": "The Associated Press-NORC Center for Public Affairs Research",
          "subject": "Favor Conducting Targeted Airstrikes to Kill Iranian Leaders",
          "end_date": "2026-03-23",
          "sample_size": "1150",
          "pos": 39.0,
          "neg": 28.0,
          "weight": 0.0643
        },
        {
          "pollster": "The Associated Press-NORC Center for Public Affairs Research",
          "subject": "Favor Deploying U.S. Troops on Ground to Fight Iran",
          "end_date": "2026-03-23",
          "sample_size": "1150",
          "pos": 62.0,
          "neg": 26.0,
          "weight": 0.0643
        },
        {
          "pollster": "The Associated Press-NORC Center for Public Affairs Research",
          "subject": "Support for Conducting Airstrikes Against Iranian Military Targets",
          "end_date": "2026-03-23",
          "sample_size": "1150",
          "pos": 39.0,
          "neg": 26.0,
          "weight": 0.0643
        },
        {
          "pollster": "The Associated Press-NORC Center for Public Affairs Research",
          "subject": "Support for Conducting Targeted Airstrikes to Kill Iranian Leaders",
          "end_date": "2026-03-23",
          "sample_size": "1150",
          "pos": 39.0,
          "neg": 28.0,
          "weight": 0.0643
        },
        {
          "pollster": "The Associated Press-NORC Center for Public Affairs Research",
          "subject": "Support for Deploying U.S. Troops on Ground to Fight Iran",
          "end_date": "2026-03-23",
          "sample_size": "1150",
          "pos": 62.0,
          "neg": 26.0,
          "weight": 0.0643
        },
        {
          "pollster": "The Associated Press-NORC Center for Public Affairs Research",
          "subject": "War in Iran - Conducting Airstrikes Against Military Targets",
          "end_date": "2026-03-23",
          "sample_size": "1150",
          "pos": 39.0,
          "neg": 26.0,
          "weight": 0.0643
        },
        {
          "pollster": "The Associated Press-NORC Center for Public Affairs Research",
          "subject": "War in Iran - Conducting Targeted Airstrikes to Kill Iranian Leaders",
          "end_date": "2026-03-23",
          "sample_size": "1150",
          "pos": 39.0,
          "neg": 28.0,
          "weight": 0.0643
        },
        {
          "pollster": "The Associated Press-NORC Center for Public Affairs Research",
          "subject": "War in Iran - Deploying U.S. Troops on Ground",
          "end_date": "2026-03-23",
          "sample_size": "1150",
          "pos": 62.0,
          "neg": 26.0,
          "weight": 0.0643
        },
        {
          "pollster": "The Associated Press-NORC Center for Public Affairs Research",
          "subject": "War in Iran - Sending Government Funds to Aid Israel's Military",
          "end_date": "2026-03-23",
          "sample_size": "1150",
          "pos": 48.0,
          "neg": 30.0,
          "weight": 0.0643
        },
        {
          "pollster": "AP-NORC Center for Public Affairs Research",
          "subject": "Recent U.S. Military Action Against Iran Assessment",
          "end_date": "2026-03-23",
          "sample_size": "1150",
          "pos": 59.0,
          "neg": 13.0,
          "weight": 0.2145
        },
        {
          "pollster": "AP-NORC Center for Public Affairs Research",
          "subject": "Support for Conducting Airstrikes Against Military Targets Inside Iran",
          "end_date": "2026-03-23",
          "sample_size": "1150",
          "pos": 39.0,
          "neg": 26.0,
          "weight": 0.2145
        },
        {
          "pollster": "AP-NORC Center for Public Affairs Research",
          "subject": "Support for Conducting Targeted Airstrikes to Kill Iranian Leaders",
          "end_date": "2026-03-23",
          "sample_size": "1150",
          "pos": 39.0,
          "neg": 28.0,
          "weight": 0.2145
        },
        {
          "pollster": "AP-NORC Center for Public Affairs Research",
          "subject": "Support for Deploying U.S. Troops on Ground to Fight Iran",
          "end_date": "2026-03-23",
          "sample_size": "1150",
          "pos": 62.0,
          "neg": 26.0,
          "weight": 0.2145
        },
        {
          "pollster": "Associated Press-NORC Center for Public Affairs Research",
          "subject": "U.S. Military Action Against Iran \u2014 Gone Too Far?",
          "end_date": "2026-03-23",
          "sample_size": "1150",
          "pos": 59.0,
          "neg": 13.0,
          "weight": 0.0643
        },
        {
          "pollster": "Associated Press-NORC Center for Public Affairs Research",
          "subject": "Position on Conducting Airstrikes Against Military Targets Inside Iran",
          "end_date": "2026-03-23",
          "sample_size": "1150",
          "pos": 39.0,
          "neg": 26.0,
          "weight": 0.0643
        },
        {
          "pollster": "Associated Press-NORC Center for Public Affairs Research",
          "subject": "Position on Conducting Targeted Airstrikes to Kill Iranian Leaders",
          "end_date": "2026-03-23",
          "sample_size": "1150",
          "pos": 39.0,
          "neg": 28.0,
          "weight": 0.0643
        },
        {
          "pollster": "Associated Press-NORC Center for Public Affairs Research",
          "subject": "Position on Deploying U.S. Troops on Ground to Fight Iran",
          "end_date": "2026-03-23",
          "sample_size": "1150",
          "pos": 62.0,
          "neg": 26.0,
          "weight": 0.0643
        }
      ]
    },
    "trump_economy": {
      "label": "Trump Economy Approval",
      "subtitle": "Approve or disapprove of Trump's handling of the economy",
      "last_updated": "2026-03-23",
      "polls_in_average": 10,
      "current": {
        "pos": 38.0,
        "neg": 61.0,
        "net": -23.0,
        "pos_label": "Approve",
        "neg_label": "Disapprove"
      },
      "polls_used": [
        {
          "pollster": "The Associated Press-NORC Center for Public Affairs Research",
          "subject": "Trump Handling the Economy",
          "end_date": "2026-03-23",
          "sample_size": "1150",
          "pos": 38.0,
          "neg": 61.0,
          "weight": 0.0643
        },
        {
          "pollster": "The Associated Press-NORC Center for Public Affairs Research",
          "subject": "Trump Handling Trade Negotiations",
          "end_date": "2026-03-23",
          "sample_size": "1150",
          "pos": 38.0,
          "neg": 61.0,
          "weight": 0.0643
        },
        {
          "pollster": "The Associated Press-NORC Center for Public Affairs Research",
          "subject": "Trump Approval of Economy",
          "end_date": "2026-03-23",
          "sample_size": "1150",
          "pos": 38.0,
          "neg": 61.0,
          "weight": 0.0643
        },
        {
          "pollster": "The Associated Press-NORC Center for Public Affairs Research",
          "subject": "Trump Approval of Trade Negotiations",
          "end_date": "2026-03-23",
          "sample_size": "1150",
          "pos": 38.0,
          "neg": 61.0,
          "weight": 0.0643
        },
        {
          "pollster": "The Associated Press-NORC Center for Public Affairs Research",
          "subject": "Trump Approval - Economy",
          "end_date": "2026-03-23",
          "sample_size": "1150",
          "pos": 38.0,
          "neg": 61.0,
          "weight": 0.0643
        },
        {
          "pollster": "The Associated Press-NORC Center for Public Affairs Research",
          "subject": "Trump Approval - Trade Negotiations",
          "end_date": "2026-03-23",
          "sample_size": "1150",
          "pos": 38.0,
          "neg": 61.0,
          "weight": 0.0643
        },
        {
          "pollster": "AP-NORC Center for Public Affairs Research",
          "subject": "Trump Approval on The Economy",
          "end_date": "2026-03-23",
          "sample_size": "1150",
          "pos": 38.0,
          "neg": 61.0,
          "weight": 0.2145
        },
        {
          "pollster": "AP-NORC Center for Public Affairs Research",
          "subject": "Trump Approval on Trade Negotiations",
          "end_date": "2026-03-23",
          "sample_size": "1150",
          "pos": 38.0,
          "neg": 61.0,
          "weight": 0.2145
        },
        {
          "pollster": "Associated Press-NORC Center for Public Affairs Research",
          "subject": "Trump Approval \u2014 The Economy",
          "end_date": "2026-03-23",
          "sample_size": "1150",
          "pos": 38.0,
          "neg": 61.0,
          "weight": 0.0643
        },
        {
          "pollster": "Associated Press-NORC Center for Public Affairs Research",
          "subject": "Trump Approval \u2014 Trade Negotiations with Other Countries",
          "end_date": "2026-03-23",
          "sample_size": "1150",
          "pos": 38.0,
          "neg": 61.0,
          "weight": 0.0643
        }
      ]
    }
  }
}